wargame/__init__.py
wargame/abstractgameunit.py
wargame/attackoftheors.py
wargame/gameuniterror.py
wargame/gameutils.py
wargame/hut.py
wargame/knight.py
wargame/orcider.py
chys-2.1.2.dist-info/LICENSE.txt
chys-2.1.2.dist-info/METADATA
chys-2.1.2.dist-info/WHEEL
chys-2.1.2.dist-info/top_level.txt
chys-2.1.2.dist-info/RECORD
