Metadata-Version: 2.1
Name: chys
Version: 2.1.2
Summary: my game
Home-page: https://test.pypi.org/legacy
Author: luoquan
Author-email: 178517202@qq.com
License: UNKNOWN
Platform: UNKNOWN
License-File: LICENSE.txt
